{"tripId":"hc_hc919_v1_b","trainNumber":"HC_HC919_V1_B","headsign":"Joliet","line":"HC","lineSlug":"hc","lineName":"Heritage Corridor Line","serviceType":"weekday","directionId":0,"stops":[{"sequence":1,"stationName":"Chicago Union Station","slug":"chicago-union-station","arrival":"5:30 PM","departure":"5:30 PM"},{"sequence":7,"stationName":"Summit","slug":"summit","arrival":"5:54 PM","departure":"5:54 PM"},{"sequence":9,"stationName":"Willow Springs","slug":"willow-springs","arrival":"6:02 PM","departure":"6:02 PM"},{"sequence":10,"stationName":"Lemont","slug":"lemont","arrival":"6:11 PM","departure":"6:11 PM"},{"sequence":11,"stationName":"Romeoville","slug":"romeoville","arrival":"6:15 PM","departure":"6:15 PM"},{"sequence":12,"stationName":"Lockport","slug":"lockport","arrival":"6:21 PM","departure":"6:21 PM"},{"sequence":13,"stationName":"Joliet","slug":"joliet","arrival":"6:36 PM","departure":"6:36 PM"}]}