{"tripId":"md-n_mn2614_v7_a","trainNumber":"MD-N_MN2614_V7_A","headsign":"Chicago Union Station","line":"MD-N","lineSlug":"md-n","lineName":"Milwaukee District North Line","serviceType":"saturday","directionId":1,"stops":[{"sequence":1,"stationName":"Fox Lake","slug":"fox-lake","arrival":"2:45 PM","departure":"2:45 PM"},{"sequence":2,"stationName":"Ingleside","slug":"ingleside","arrival":"2:48 PM","departure":"2:48 PM"},{"sequence":3,"stationName":"Long Lake","slug":"long-lake","arrival":"2:51 PM","departure":"2:51 PM"},{"sequence":4,"stationName":"Round Lake","slug":"round-lake","arrival":"2:54 PM","departure":"2:54 PM"},{"sequence":5,"stationName":"Grayslake","slug":"grayslake","arrival":"3:00 PM","departure":"3:00 PM"},{"sequence":9,"stationName":"Prairie Crossing","slug":"prairie-crossing-metra","arrival":"3:04 PM","departure":"3:04 PM"},{"sequence":10,"stationName":"Libertyville","slug":"libertyville","arrival":"3:10 PM","departure":"3:10 PM"},{"sequence":12,"stationName":"Lake Forest","slug":"lake-forest-metra","arrival":"3:20 PM","departure":"3:20 PM"},{"sequence":13,"stationName":"Deerfield","slug":"deerfield","arrival":"3:26 PM","departure":"3:26 PM"},{"sequence":14,"stationName":"Lake-Cook","slug":"lake-cook","arrival":"3:29 PM","departure":"3:29 PM"},{"sequence":15,"stationName":"Northbrook","slug":"northbrook","arrival":"3:33 PM","departure":"3:33 PM"},{"sequence":16,"stationName":"Glen/N. Glenview","slug":"glen-n-glenview","arrival":"3:37 PM","departure":"3:37 PM"},{"sequence":17,"stationName":"Glenview","slug":"glenview","arrival":"3:40 PM","departure":"3:40 PM"},{"sequence":18,"stationName":"Golf","slug":"golf","arrival":"3:43 PM","departure":"3:43 PM"},{"sequence":19,"stationName":"Morton Grove","slug":"morton-grove","arrival":"3:46 PM","departure":"3:46 PM"},{"sequence":20,"stationName":"Edgebrook","slug":"edgebrook","arrival":"3:51 PM","departure":"3:51 PM"},{"sequence":21,"stationName":"Forest Glen","slug":"forest-glen","arrival":"3:54 PM","departure":"3:54 PM"},{"sequence":24,"stationName":"Mayfair","slug":"mayfair","arrival":"3:57 PM","departure":"3:57 PM"},{"sequence":25,"stationName":"Grayland","slug":"grayland","arrival":"3:59 PM","departure":"3:59 PM"},{"sequence":26,"stationName":"Healy","slug":"healy","arrival":"4:02 PM","departure":"4:02 PM"},{"sequence":28,"stationName":"Western Ave","slug":"western-ave","arrival":"4:08 PM","departure":"4:08 PM"},{"sequence":31,"stationName":"Chicago Union Station","slug":"chicago-union-station","arrival":"4:22 PM","departure":"4:22 PM"}]}